main.py
PackageExampleBunyaminergen-0.1.dist-info/LICENSE
PackageExampleBunyaminergen-0.1.dist-info/METADATA
PackageExampleBunyaminergen-0.1.dist-info/WHEEL
PackageExampleBunyaminergen-0.1.dist-info/top_level.txt
PackageExampleBunyaminergen-0.1.dist-info/RECORD
